matorage/__init__.py
matorage/config.py
matorage/connector.py
matorage/downloader.py
matorage/nas.py
matorage/serialize.py
matorage/testing_utils.py
matorage/uploader.py
matorage/utils.py
matorage/data/__init__.py
matorage/data/attribute.py
matorage/data/config.py
matorage/data/data.py
matorage/data/metadata.py
matorage/data/saver.py
matorage/data/tensorflow/__init__.py
matorage/data/tensorflow/v2/__init__.py
matorage/data/tensorflow/v2/dataset.py
matorage/data/torch/__init__.py
matorage/data/torch/dataset.py
matorage/model/__init__.py
matorage/model/config.py
matorage/model/manager.py
matorage/model/tensorflow/__init__.py
matorage/model/tensorflow/v2/__init__.py
matorage/model/tensorflow/v2/manager.py
matorage/model/torch/__init__.py
matorage/model/torch/manager.py
matorage/optimizer/__init__.py
matorage/optimizer/config.py
matorage/optimizer/manager.py
matorage/optimizer/tensorflow/__init__.py
matorage/optimizer/tensorflow/v2/__init__.py
matorage/optimizer/tensorflow/v2/manager.py
matorage/optimizer/torch/__init__.py
matorage/optimizer/torch/manager.py
matorage/tensorflow/__init__.py
matorage/torch/__init__.py
tests/__init__.py
tests/test_data.py
tests/test_datasaver.py
tests/test_model.py
tests/test_nas.py
tests/test_optimizer.py
tests/test_storage.py
tests/test_suite.py
tests/test_tf_data.py
tests/test_tf_model.py
tests/test_tf_optimizer.py
tests/test_torch_data.py
tests/test_torch_model.py
tests/test_torch_optimizer.py
matorage-0.3.0.dist-info/LICENSE
matorage-0.3.0.dist-info/METADATA
matorage-0.3.0.dist-info/NOTICE
matorage-0.3.0.dist-info/WHEEL
matorage-0.3.0.dist-info/top_level.txt
matorage-0.3.0.dist-info/RECORD
